{
  "workload": "container/postgres-anchor",
  "image": "postgres:17",
  "observation_window_description": "60 s of pgbench at 10 clients (~3,750 tps; 112,534 transactions) on a freshly-initialised pgbench dataset",
  "observation_source": "/proc/<pid>/maps of all postgres-anchor processes, mapped to Debian packages via dpkg-query -S",
  "_note": "This is a real runtime observation, not synthetic. It substitutes for a Falco event stream in the present prototype: Falco's eBPF rules would surface the same shared-library file-open events; we read them from /proc instead. See chapter 6 §6.5.4.",
  "loaded_packages": [
    "libaudit1",
    "libc6",
    "libcap-ng0",
    "libcap2",
    "libcom-err2",
    "libgcc-s1",
    "libgssapi-krb5-2",
    "libicu76",
    "libk5crypto3",
    "libkeyutils1",
    "libkrb5-3",
    "libkrb5support0",
    "libldap2",
    "liblz4-1",
    "liblzma5",
    "libpam0g",
    "libsasl2-2",
    "libssl3t64",
    "libstdc++6",
    "libsystemd0",
    "libxml2",
    "libxxhash0",
    "libzstd1",
    "zlib1g"
  ],
  "observed_symbols": []
}
